{
  "currency": "AED",
  "priceDisplay": "monthly_equivalent",
  "defaultTerm": {
    "months": 36,
    "label": {
      "en": "3-year term",
      "ar": "اشتراك 3 سنوات"
    },
    "discountPercent": 15
  },
  "availableDiscounts": [
    {
      "months": 12,
      "discountPercent": 0,
      "label": {
        "en": "1 year",
        "ar": "سنة واحدة"
      }
    },
    {
      "months": 24,
      "discountPercent": 10,
      "label": {
        "en": "2 years with 10% discount",
        "ar": "سنتان مع خصم 10%"
      }
    },
    {
      "months": 36,
      "discountPercent": 15,
      "label": {
        "en": "3 years with 15% discount",
        "ar": "3 سنوات مع خصم 15%"
      }
    }
  ],
  "billingNote": {
    "en": "Monthly-equivalent prices are based on the selected long-term billing option. Website and online store free-start plans can begin on a Skilled Host subdomain, then upgrade later to a custom domain, hosting, business email, SSL, security and backup services. Final billing totals, available terms and renewal prices are shown at checkout. Free first-year domain applies only to eligible paid packages and selected extensions.",
    "ar": "الأسعار المعروضة هي السعر الشهري التقريبي حسب خيار الدفع طويل المدة. يمكن بدء باقات المواقع والمتاجر المجانية على نطاق فرعي من Skilled Host، ثم الترقية لاحقاً إلى نطاق خاص واستضافة وبريد أعمال وSSL وحماية ونسخ احتياطي. تظهر المبالغ النهائية وخيارات الدفع وأسعار التجديد داخل صفحة إتمام الطلب. النطاق المجاني للسنة الأولى ينطبق فقط على الباقات المدفوعة المؤهلة وامتدادات محددة."
  },
  "categories": [
    {
      "id": "website-packages",
      "label": {
        "en": "Website Packages",
        "ar": "باقات المواقع"
      },
      "title": {
        "en": "Website Packages",
        "ar": "باقات المواقع"
      },
      "description": {
        "en": "Start with a free SEO-ready website theme on a Skilled Host subdomain. Customize your sections, use AI-assisted content and upgrade when you are ready for a custom domain, business email, SSL, backups and professional support.",
        "ar": "ابدأ بقالب موقع مجاني وجاهز لمحركات البحث على نطاق فرعي من Skilled Host. خصص الأقسام، واستخدم مساعدة المحتوى بالذكاء الاصطناعي، ثم قم بالترقية عندما تكون جاهزاً لنطاق خاص وبريد أعمال وSSL ونسخ احتياطي ودعم احترافي."
      },
      "categoryUrl": "https://cp.skilledhost.com/pccategory?cat=5255",
      "pageUrl": "/website-packages",
      "plans": [
        {
          "name": {
            "en": "Website Free Start",
            "ar": "بداية مجانية للموقع"
          },
          "priceMonthly": 0,
          "orderUrl": "#theme-categories",
          "badge": {
            "en": "Free Start",
            "ar": "بداية مجانية"
          },
          "cta": {
            "en": "Start Free",
            "ar": "ابدأ مجاناً"
          },
          "features": {
            "en": [
              "Free Skilled Host Subdomain",
              "Professional Website Theme Included",
              "Website Editor Included",
              "Flexible Section Variations",
              "SEO-Ready Page Structure",
              "AI Content Assistant",
              "Mobile-Ready Pages",
              "Contact Section Included",
              "Upgrade Anytime",
              "Custom Domain and Business Email Not Included"
            ],
            "ar": [
              "نطاق فرعي مجاني من Skilled Host",
              "قالب موقع احترافي مدمج",
              "محرر الموقع مدمج",
              "تصاميم مرنة للأقسام",
              "هيكل صفحات جاهز لمحركات البحث",
              "مساعد محتوى بالذكاء الاصطناعي",
              "صفحات متجاوبة مع الجوال",
              "قسم تواصل مدمج",
              "إمكانية الترقية في أي وقت",
              "النطاق الخاص وبريد الأعمال غير مدمجين"
            ]
          }
        },
        {
          "name": {
            "en": "Website Business",
            "ar": "باقة موقع Business"
          },
          "priceMonthly": 50,
          "orderUrl": "https://cp.skilledhost.com/domain-required?p=294887-1-lhr&t=36",
          "badge": {
            "en": "Business",
            "ar": "للأعمال"
          },
          "cta": {
            "en": "Upgrade to Business",
            "ar": "الترقية إلى Business"
          },
          "features": {
            "en": [
              "Everything in Website Free Start",
              "Custom Domain Connection",
              "Free First-Year Domain",
              "Unlimited SSD Web Space",
              "20 × 10GB Business Mailboxes",
              "Free SSL Setup",
              "Website Backup Included",
              "Domain Connection Support",
              "Malware Scanning",
              "No File or Server Access Required"
            ],
            "ar": [
              "كل ما في البداية المجانية للموقع",
              "ربط نطاق خاص",
              "نطاق مجاني للسنة الأولى",
              "مساحة SSD غير محدودة",
              "20 صندوق بريد أعمال 10GB",
              "إعداد SSL مجاني",
              "نسخ احتياطي للموقع مدمج",
              "دعم ربط النطاق",
              "فحص البرمجيات الضارة",
              "لا حاجة للوصول إلى الملفات أو الخادم"
            ]
          }
        },
        {
          "name": {
            "en": "Website Pro",
            "ar": "باقة موقع Pro"
          },
          "priceMonthly": 64,
          "orderUrl": "https://cp.skilledhost.com/domain-required?p=294889-1-lhr&t=36",
          "badge": {
            "en": "Popular",
            "ar": "الأكثر طلباً"
          },
          "cta": {
            "en": "Choose Pro",
            "ar": "اختر Pro"
          },
          "features": {
            "en": [
              "Everything in Website Business",
              "More Section Layout Options",
              "Advanced SEO Page Structure",
              "AI-Assisted Content Support",
              "Unlimited SSD Web Space",
              "50 × 10GB Business Mailboxes",
              "Free SSL Setup",
              "Website Backup Included",
              "Domain Connection Support",
              "No File or Server Access Required"
            ],
            "ar": [
              "كل ما في باقة موقع Business",
              "خيارات أكثر لتصاميم الأقسام",
              "هيكل صفحات SEO متقدم",
              "دعم محتوى بالذكاء الاصطناعي",
              "مساحة SSD غير محدودة",
              "50 صندوق بريد أعمال 10GB",
              "إعداد SSL مجاني",
              "نسخ احتياطي للموقع مدمج",
              "دعم ربط النطاق",
              "لا حاجة للوصول إلى الملفات أو الخادم"
            ]
          }
        },
        {
          "name": {
            "en": "Website Ultimate",
            "ar": "باقة موقع Ultimate"
          },
          "priceMonthly": 85,
          "orderUrl": "https://cp.skilledhost.com/domain-required?p=119534-1-lhr&t=36",
          "badge": {
            "en": "Advanced",
            "ar": "متقدمة"
          },
          "cta": {
            "en": "Choose Ultimate",
            "ar": "اختر Ultimate"
          },
          "features": {
            "en": [
              "Everything in Website Pro",
              "Advanced Website Structure",
              "More Page and Section Flexibility",
              "Priority Launch Support",
              "Unlimited SSD Web Space",
              "Unlimited × 10GB Business Mailboxes",
              "Free SSL Setup",
              "Website Backup Included",
              "Domain Connection Support",
              "No File or Server Access Required"
            ],
            "ar": [
              "كل ما في باقة موقع Pro",
              "هيكل موقع متقدم",
              "مرونة أكبر للصفحات والأقسام",
              "دعم أولوية عند الإطلاق",
              "مساحة SSD غير محدودة",
              "صناديق بريد أعمال 10GB غير محدودة",
              "إعداد SSL مجاني",
              "نسخ احتياطي للموقع مدمج",
              "دعم ربط النطاق",
              "لا حاجة للوصول إلى الملفات أو الخادم"
            ]
          }
        }
      ]
    },
    {
      "id": "online-store-packages",
      "label": {
        "en": "Online Store",
        "ar": "المتجر الإلكتروني"
      },
      "title": {
        "en": "Online Store Packages",
        "ar": "باقات المتاجر الإلكترونية"
      },
      "description": {
        "en": "Start with a free online store theme and Skilled Host subdomain. Build your store pages, prepare products and categories, use SEO tools and AI-assisted content, then upgrade when you are ready for checkout, domain, email, SSL, backup and support.",
        "ar": "ابدأ بقالب متجر إلكتروني مجاني ونطاق فرعي من Skilled Host. أنشئ صفحات المتجر، وجهز المنتجات والتصنيفات، واستخدم أدوات SEO ومساعدة المحتوى بالذكاء الاصطناعي، ثم قم بالترقية عندما تكون جاهزاً لإتمام الطلب والنطاق والبريد وSSL والنسخ الاحتياطي والدعم."
      },
      "categoryUrl": "https://cp.skilledhost.com/pccategory?cat=5257",
      "pageUrl": "/online-store-packages",
      "plans": [
        {
          "name": {
            "en": "Store Free Start",
            "ar": "بداية مجانية للمتجر"
          },
          "priceMonthly": 0,
          "orderUrl": "#theme-categories",
          "badge": {
            "en": "Free Start",
            "ar": "بداية مجانية"
          },
          "cta": {
            "en": "Start free",
            "ar": "ابدأ مجاناً"
          },
          "features": {
            "en": [
              "Free Skilled Host Subdomain",
              "Professional Store Theme Included",
              "Store Editor Included",
              "Flexible Section Variations",
              "Product Page Layouts",
              "Category Page Layouts",
              "SEO-Ready Store Structure",
              "AI Content Assistant",
              "Mobile-Ready Store Pages",
              "Checkout and Custom Domain Not Included"
            ],
            "ar": [
              "نطاق فرعي مجاني من Skilled Host",
              "قالب متجر احترافي مدمج",
              "محرر المتجر مدمج",
              "تصاميم مرنة للأقسام",
              "تصاميم صفحات المنتجات",
              "تصاميم صفحات التصنيفات",
              "هيكل متجر جاهز لمحركات البحث",
              "مساعد محتوى بالذكاء الاصطناعي",
              "صفحات متجر متجاوبة مع الجوال",
              "إتمام الطلب والنطاق الخاص غير مدمجين"
            ]
          }
        },
        {
          "name": {
            "en": "Online Store Business",
            "ar": "باقة متجر Business"
          },
          "priceMonthly": 50,
          "orderUrl": "https://cp.skilledhost.com/domain-required?p=294897-1-lhr&t=36",
          "badge": {
            "en": "Business",
            "ar": "للأعمال"
          },
          "cta": {
            "en": "Upgrade to Business",
            "ar": "الترقية إلى Business"
          },
          "features": {
            "en": [
              "Everything in Store Free Start",
              "Checkout Setup Included",
              "Custom Domain Connection",
              "Free First-Year Domain",
              "Unlimited SSD Web Space",
              "20 × 10GB Business Mailboxes",
              "Product Pages Included",
              "Category Pages Included",
              "Free SSL Setup",
              "Website Backup Included"
            ],
            "ar": [
              "كل ما في البداية المجانية للمتجر",
              "إعداد الطلب مدمج",
              "ربط نطاق خاص",
              "نطاق مجاني للسنة الأولى",
              "مساحة SSD غير محدودة",
              "20 صندوق بريد أعمال 10GB",
              "صفحات المنتجات مدمجة",
              "صفحات التصنيفات مدمجة",
              "إعداد SSL مجاني",
              "نسخ احتياطي للموقع مدمج"
            ]
          }
        },
        {
          "name": {
            "en": "Online Store Pro",
            "ar": "باقة متجر Pro"
          },
          "priceMonthly": 64,
          "orderUrl": "https://cp.skilledhost.com/domain-required?p=294899-1-lhr&t=36",
          "badge": {
            "en": "Popular",
            "ar": "الأكثر طلباً"
          },
          "cta": {
            "en": "Choose Pro",
            "ar": "اختر Pro"
          },
          "features": {
            "en": [
              "Everything in Online Store Business",
              "More Store Section Options",
              "Advanced Store Page Structure",
              "AI-Assisted Product Content Support",
              "Unlimited SSD Web Space",
              "50 × 10GB Business Mailboxes",
              "Product Pages Included",
              "Category Pages Included",
              "Checkout Setup Included",
              "Website Backup Included"
            ],
            "ar": [
              "كل ما في باقة متجر Business",
              "خيارات أكثر لأقسام المتجر",
              "هيكل صفحات متجر متقدم",
              "دعم محتوى المنتجات بالذكاء الاصطناعي",
              "مساحة SSD غير محدودة",
              "50 صندوق بريد أعمال 10GB",
              "صفحات المنتجات مدمجة",
              "صفحات التصنيفات مدمجة",
              "إعداد الطلب مدمج",
              "نسخ احتياطي للموقع مدمج"
            ]
          }
        },
        {
          "name": {
            "en": "Online Store Ultimate",
            "ar": "باقة متجر Ultimate"
          },
          "priceMonthly": 85,
          "orderUrl": "https://cp.skilledhost.com/domain-required?p=294901-1-lhr&t=36",
          "badge": {
            "en": "Advanced",
            "ar": "متقدمة"
          },
          "cta": {
            "en": "Choose Ultimate",
            "ar": "اختر Ultimate"
          },
          "features": {
            "en": [
              "Everything in Online Store Pro",
              "Advanced Store Structure",
              "More Product and Category Flexibility",
              "Priority Launch Support",
              "Unlimited SSD Web Space",
              "Unlimited × 10GB Business Mailboxes",
              "Product Pages Included",
              "Category Pages Included",
              "Checkout Setup Included",
              "Website Backup Included"
            ],
            "ar": [
              "كل ما في باقة متجر Pro",
              "هيكل متجر متقدم",
              "مرونة أكبر للمنتجات والتصنيفات",
              "دعم أولوية عند الإطلاق",
              "مساحة SSD غير محدودة",
              "صناديق بريد أعمال 10GB غير محدودة",
              "صفحات المنتجات مدمجة",
              "صفحات التصنيفات مدمجة",
              "إعداد الطلب مدمج",
              "نسخ احتياطي للموقع مدمج"
            ]
          }
        }
      ]
    },
    {
      "id": "web-hosting",
      "label": {
        "en": "Web Hosting",
        "ar": "استضافة المواقع"
      },
      "title": {
        "en": "Web Hosting Plans",
        "ar": "خطط استضافة المواقع"
      },
      "description": {
        "en": "Reliable paid hosting for existing websites, landing pages, portfolios, blogs and company profiles that need direct hosting access.",
        "ar": "استضافة مدفوعة وموثوقة للمواقع الحالية والصفحات التعريفية والمعارض الرقمية والمدونات التي تحتاج إلى وصول مباشر للاستضافة."
      },
      "categoryUrl": "https://cp.skilledhost.com/pccategory?cat=5191",
      "pageUrl": "/web-hosting",
      "plans": [
        {
          "name": {
            "en": "Starter",
            "ar": "Starter"
          },
          "priceMonthly": 21,
          "orderUrl": "https://cp.skilledhost.com/domain-required?p=29273-1&t=36",
          "badge": {
            "en": "Starter",
            "ar": "بداية"
          },
          "features": {
            "en": [
              "1 Website",
              "100GB SSD Web Space",
              "Unmetered Bandwidth",
              "5 × 10GB Mailboxes",
              "Free Wildcard SSL Certificates",
              "1 MySQL Database",
              "Malware Scanning",
              "DDoS Protection",
              "Website Builder Included"
            ],
            "ar": [
              "موقع واحد",
              "100GB مساحة SSD",
              "نقل بيانات غير محدود",
              "5 صناديق بريد 10GB",
              "شهادات SSL مجانية",
              "قاعدة بيانات MySQL واحدة",
              "فحص البرمجيات الضارة",
              "حماية DDoS",
              "منشئ مواقع مدمج"
            ]
          }
        },
        {
          "name": {
            "en": "Business",
            "ar": "Business"
          },
          "priceMonthly": 35,
          "orderUrl": "https://cp.skilledhost.com/domain-required?p=36509-1-lhr&t=36",
          "badge": {
            "en": "Popular",
            "ar": "الأكثر طلباً"
          },
          "features": {
            "en": [
              "Up to 5 Websites",
              "Free First-Year Domain",
              "1000GB SSD Web Space",
              "Unmetered Bandwidth",
              "20 × 10GB Mailboxes",
              "Free Wildcard SSL Certificates",
              "5 MySQL Databases",
              "Malware Scanning",
              "DDoS Protection",
              "Daily Backup Access"
            ],
            "ar": [
              "حتى 5 مواقع",
              "نطاق مجاني للسنة الأولى",
              "1000GB مساحة SSD",
              "نقل بيانات غير محدود",
              "20 صندوق بريد 10GB",
              "شهادات SSL مجانية",
              "5 قواعد بيانات MySQL",
              "فحص البرمجيات الضارة",
              "حماية DDoS",
              "نسخ احتياطي يومي"
            ]
          }
        },
        {
          "name": {
            "en": "Pro",
            "ar": "Pro"
          },
          "priceMonthly": 50,
          "orderUrl": "https://cp.skilledhost.com/domain-required?p=36507-1-lhr&t=36",
          "badge": {
            "en": "Growth",
            "ar": "للنمو"
          },
          "features": {
            "en": [
              "Up to 10 Websites",
              "Free First-Year Domain",
              "Unlimited SSD Web Space",
              "Unmetered Bandwidth",
              "50 × 10GB Mailboxes",
              "Free Wildcard SSL Certificates",
              "10 MySQL Databases",
              "SSH Access",
              "Remote MySQL Access",
              "Timeline Backups"
            ],
            "ar": [
              "حتى 10 مواقع",
              "نطاق مجاني للسنة الأولى",
              "مساحة SSD غير محدودة",
              "نقل بيانات غير محدود",
              "50 صندوق بريد 10GB",
              "شهادات SSL مجانية",
              "10 قواعد بيانات MySQL",
              "دخول SSH",
              "دخول Remote MySQL",
              "نسخ احتياطي زمني"
            ]
          }
        },
        {
          "name": {
            "en": "Ultimate",
            "ar": "Ultimate"
          },
          "priceMonthly": 70,
          "orderUrl": "https://cp.skilledhost.com/domain-required?p=32089-1-lhr&t=36",
          "badge": {
            "en": "Advanced",
            "ar": "متقدمة"
          },
          "features": {
            "en": [
              "Unlimited Websites",
              "Free First-Year Domain",
              "Unlimited SSD Web Space",
              "Unlimited Bandwidth",
              "Unlimited × 10GB Mailboxes",
              "Free Wildcard SSL Certificates",
              "Unlimited MySQL Databases",
              "SSH Access",
              "Remote MySQL Access",
              "Timeline Backups"
            ],
            "ar": [
              "مواقع غير محدودة",
              "نطاق مجاني للسنة الأولى",
              "مساحة SSD غير محدودة",
              "نقل بيانات غير محدود",
              "صناديق بريد 10GB غير محدودة",
              "شهادات SSL مجانية",
              "قواعد بيانات MySQL غير محدودة",
              "دخول SSH",
              "دخول Remote MySQL",
              "نسخ احتياطي زمني"
            ]
          }
        }
      ]
    },
    {
      "id": "wordpress-hosting",
      "label": {
        "en": "WordPress",
        "ar": "ووردبريس"
      },
      "title": {
        "en": "WordPress Hosting Plans",
        "ar": "خطط استضافة ووردبريس"
      },
      "description": {
        "en": "Optimised paid hosting for WordPress websites, blogs, company pages and content platforms that need WordPress-ready performance and support.",
        "ar": "استضافة مدفوعة ومحسّنة لمواقع ووردبريس والمدونات وصفحات الشركات ومنصات المحتوى التي تحتاج أداء ودعماً مناسباً لووردبريس."
      },
      "categoryUrl": "https://cp.skilledhost.com/pccategory?cat=5193",
      "pageUrl": "/wordpress-hosting",
      "plans": [
        {
          "name": {
            "en": "Starter",
            "ar": "Starter"
          },
          "priceMonthly": 21,
          "orderUrl": "https://cp.skilledhost.com/domain-required?p=29271-1-lhr&t=36",
          "badge": {
            "en": "Starter",
            "ar": "بداية"
          },
          "features": {
            "en": [
              "1 WordPress Website",
              "50GB SSD Web Space",
              "Unmetered Bandwidth",
              "5 × 10GB Mailboxes",
              "Free Wildcard SSL Certificates",
              "1 MySQL Database",
              "Malware Scanning",
              "DDoS Protection",
              "WordPress Tools Included"
            ],
            "ar": [
              "موقع ووردبريس واحد",
              "50GB مساحة SSD",
              "نقل بيانات غير محدود",
              "5 صناديق بريد 10GB",
              "شهادات SSL مجانية",
              "قاعدة بيانات MySQL واحدة",
              "فحص البرمجيات الضارة",
              "حماية DDoS",
              "أدوات ووردبريس مدمجة"
            ]
          }
        },
        {
          "name": {
            "en": "Business",
            "ar": "Business"
          },
          "priceMonthly": 35,
          "orderUrl": "https://cp.skilledhost.com/domain-required?p=34097-1-lhr&t=36",
          "badge": {
            "en": "Popular",
            "ar": "الأكثر طلباً"
          },
          "features": {
            "en": [
              "1 WordPress Website",
              "Free First-Year Domain",
              "100GB SSD Web Space",
              "Unmetered Bandwidth",
              "20 × 10GB Mailboxes",
              "Free Wildcard SSL Certificates",
              "WordPress Staging Tools",
              "Daily Backup Access",
              "Malware Scanning",
              "Easy WordPress Management"
            ],
            "ar": [
              "موقع ووردبريس واحد",
              "نطاق مجاني للسنة الأولى",
              "100GB مساحة SSD",
              "نقل بيانات غير محدود",
              "20 صندوق بريد 10GB",
              "شهادات SSL مجانية",
              "أدوات Staging لووردبريس",
              "نسخ احتياطي يومي",
              "فحص البرمجيات الضارة",
              "إدارة ووردبريس سهلة"
            ]
          }
        },
        {
          "name": {
            "en": "Pro",
            "ar": "Pro"
          },
          "priceMonthly": 50,
          "orderUrl": "https://cp.skilledhost.com/domain-required?p=36365-1-lhr&t=36",
          "badge": {
            "en": "Growth",
            "ar": "للنمو"
          },
          "features": {
            "en": [
              "Professional WordPress Hosting",
              "Free First-Year Domain",
              "Unlimited SSD Web Space",
              "Unmetered Bandwidth",
              "50 × 10GB Mailboxes",
              "Free Wildcard SSL Certificates",
              "WordPress Staging Tools",
              "SSH Access",
              "Remote MySQL Access",
              "Timeline Backups Included"
            ],
            "ar": [
              "استضافة ووردبريس احترافية",
              "نطاق مجاني للسنة الأولى",
              "مساحة SSD غير محدودة",
              "نقل بيانات غير محدود",
              "50 صندوق بريد 10GB",
              "شهادات SSL مجانية",
              "أدوات Staging لووردبريس",
              "دخول SSH",
              "دخول Remote MySQL",
              "نسخ احتياطي زمني مدمج"
            ]
          }
        },
        {
          "name": {
            "en": "Ultimate",
            "ar": "Ultimate"
          },
          "priceMonthly": 70,
          "orderUrl": "https://cp.skilledhost.com/domain-required?p=34101-1-lhr&t=36",
          "badge": {
            "en": "Advanced",
            "ar": "متقدمة"
          },
          "features": {
            "en": [
              "Premium WordPress Hosting",
              "Free First-Year Domain",
              "Unlimited SSD Web Space",
              "Unlimited Bandwidth",
              "Unlimited × 10GB Mailboxes",
              "Free Wildcard SSL Certificates",
              "WordPress Staging Tools",
              "SSH Access",
              "Advanced WordPress Management Tools",
              "Timeline Backups Included"
            ],
            "ar": [
              "استضافة ووردبريس مميزة",
              "نطاق مجاني للسنة الأولى",
              "مساحة SSD غير محدودة",
              "نقل بيانات غير محدود",
              "صناديق بريد 10GB غير محدودة",
              "شهادات SSL مجانية",
              "أدوات Staging لووردبريس",
              "دخول SSH",
              "أدوات إدارة ووردبريس متقدمة",
              "نسخ احتياطي زمني مدمج"
            ]
          }
        }
      ]
    },
    {
      "id": "windows-hosting",
      "label": {
        "en": "Windows",
        "ar": "ويندوز"
      },
      "title": {
        "en": "Windows Hosting Plans",
        "ar": "خطط استضافة ويندوز"
      },
      "description": {
        "en": "Paid Windows-based hosting for websites and projects that need Microsoft technology support or Windows-compatible hosting requirements.",
        "ar": "استضافة مدفوعة مبنية على ويندوز للمواقع والمشاريع التي تحتاج دعم تقنيات مايكروسوفت أو استضافة متوافقة مع ويندوز."
      },
      "categoryUrl": "https://cp.skilledhost.com/pccategory?cat=5197",
      "pageUrl": "/windows-hosting",
      "plans": [
        {
          "name": {
            "en": "Starter",
            "ar": "Starter"
          },
          "priceMonthly": 21,
          "orderUrl": "https://cp.skilledhost.com/domain-required?p=293503-1-lhr&t=36",
          "badge": {
            "en": "Starter",
            "ar": "بداية"
          },
          "features": {
            "en": [
              "1 Windows Website",
              "50GB SSD Web Space",
              "Unmetered Bandwidth",
              "5 × 10GB Mailboxes",
              "Free Wildcard SSL Certificates",
              "1 MySQL Database",
              "5 Subdomains",
              "File Manager and FTP Access",
              "Backup and Restore Tools",
              "DDoS Protection"
            ],
            "ar": [
              "موقع ويندوز واحد",
              "50GB مساحة SSD",
              "نقل بيانات غير محدود",
              "5 صناديق بريد 10GB",
              "شهادات SSL مجانية",
              "قاعدة بيانات MySQL واحدة",
              "5 نطاقات فرعية",
              "مدير ملفات ودخول FTP",
              "أدوات النسخ والاستعادة",
              "حماية DDoS"
            ]
          }
        },
        {
          "name": {
            "en": "Business",
            "ar": "Business"
          },
          "priceMonthly": 35,
          "orderUrl": "https://cp.skilledhost.com/domain-required?p=29269-1&t=36",
          "badge": {
            "en": "Popular",
            "ar": "الأكثر طلباً"
          },
          "features": {
            "en": [
              "1 Windows Hosting Package",
              "Free First-Year Domain",
              "50GB SSD Web Space",
              "Unmetered Bandwidth",
              "20 × 10GB Mailboxes",
              "Free Wildcard SSL Certificates",
              "10 MySQL Databases",
              "10 Subdomains",
              "Website Builder Included",
              "Backup and Restore Tools"
            ],
            "ar": [
              "باقة استضافة ويندوز واحدة",
              "نطاق مجاني للسنة الأولى",
              "50GB مساحة SSD",
              "نقل بيانات غير محدود",
              "20 صندوق بريد 10GB",
              "شهادات SSL مجانية",
              "10 قواعد بيانات MySQL",
              "10 نطاقات فرعية",
              "منشئ مواقع مدمج",
              "أدوات النسخ والاستعادة"
            ]
          }
        },
        {
          "name": {
            "en": "Pro",
            "ar": "Pro"
          },
          "priceMonthly": 50,
          "orderUrl": "https://cp.skilledhost.com/domain-required?p=36513-1&t=36",
          "badge": {
            "en": "Growth",
            "ar": "للنمو"
          },
          "features": {
            "en": [
              "Professional Windows Hosting",
              "Free First-Year Domain",
              "Up to 6 Domains",
              "50GB SSD Web Space",
              "Unmetered Bandwidth",
              "30 × 10GB Mailboxes",
              "Free Wildcard SSL Certificates",
              "5 MySQL Databases",
              "10 Subdomains",
              "File Manager and FTP Access"
            ],
            "ar": [
              "استضافة ويندوز احترافية",
              "نطاق مجاني للسنة الأولى",
              "حتى 6 نطاقات",
              "50GB مساحة SSD",
              "نقل بيانات غير محدود",
              "30 صندوق بريد 10GB",
              "شهادات SSL مجانية",
              "5 قواعد بيانات MySQL",
              "10 نطاقات فرعية",
              "مدير ملفات ودخول FTP"
            ]
          }
        },
        {
          "name": {
            "en": "Ultimate",
            "ar": "Ultimate"
          },
          "priceMonthly": 70,
          "orderUrl": "https://cp.skilledhost.com/domain-required?p=43909-1&t=36",
          "badge": {
            "en": "Advanced",
            "ar": "متقدمة"
          },
          "features": {
            "en": [
              "Ultimate Windows Hosting",
              "Free First-Year Domain",
              "Unlimited Domains",
              "Unlimited SSD Web Space",
              "Unmetered Bandwidth",
              "Unlimited × 10GB Mailboxes",
              "Free Wildcard SSL Certificates",
              "Unlimited MySQL Databases",
              "Website Builder Included",
              "Backup and Restore Tools"
            ],
            "ar": [
              "استضافة ويندوز متقدمة",
              "نطاق مجاني للسنة الأولى",
              "نطاقات غير محدودة",
              "مساحة SSD غير محدودة",
              "نقل بيانات غير محدود",
              "صناديق بريد 10GB غير محدودة",
              "شهادات SSL مجانية",
              "قواعد بيانات MySQL غير محدودة",
              "منشئ مواقع مدمج",
              "أدوات النسخ والاستعادة"
            ]
          }
        }
      ]
    },
    {
      "id": "business-email",
      "label": {
        "en": "Business Email",
        "ar": "بريد الأعمال"
      },
      "title": {
        "en": "Business Email Plans",
        "ar": "خطط بريد الأعمال"
      },
      "description": {
        "en": "Professional email using your business domain, with secure mailbox hosting, webmail access, email app support, spam protection and migration help.",
        "ar": "بريد احترافي باستخدام نطاق عملك، مع استضافة بريد آمنة، دخول Webmail، دعم تطبيقات البريد، حماية من الرسائل المزعجة ومساعدة في النقل."
      },
      "categoryUrl": "https://cp.skilledhost.com/pccategory?cat=4737",
      "pageUrl": "/business-email",
      "plans": [
        {
          "name": {
            "en": "Starter",
            "ar": "Starter"
          },
          "priceMonthly": 14,
          "orderUrl": "https://cp.skilledhost.com/domain-required?p=274705-1-lhr&t=36",
          "badge": {
            "en": "Starter",
            "ar": "بداية"
          },
          "features": {
            "en": [
              "5 Business Mailboxes",
              "10GB Storage per Mailbox",
              "Professional Email Using Your Domain",
              "Webmail Access",
              "Desktop, Mobile and Tablet Access",
              "Spam and Virus Protection",
              "Outlook and Email App Support",
              "Email Migration Tools"
            ],
            "ar": [
              "5 صناديق بريد أعمال",
              "10GB لكل صندوق بريد",
              "بريد احترافي باسم نطاقك",
              "دخول Webmail",
              "دخول من الكمبيوتر والجوال والتابلت",
              "حماية من الرسائل المزعجة والفيروسات",
              "دعم Outlook وتطبيقات البريد",
              "أدوات نقل البريد"
            ]
          }
        },
        {
          "name": {
            "en": "Plus",
            "ar": "Plus"
          },
          "priceMonthly": 21,
          "orderUrl": "https://cp.skilledhost.com/domain-required?p=293505-1-lhr&t=36",
          "badge": {
            "en": "Popular",
            "ar": "الأكثر طلباً"
          },
          "features": {
            "en": [
              "20 Business Mailboxes",
              "Free First-Year Domain",
              "10GB Storage per Mailbox",
              "Professional Email Using Your Domain",
              "Webmail Access",
              "Desktop, Mobile and Tablet Access",
              "Spam and Virus Protection",
              "Outlook and Email App Support",
              "Email Forwarding and Autoresponders",
              "Email Migration Tools"
            ],
            "ar": [
              "20 صندوق بريد أعمال",
              "نطاق مجاني للسنة الأولى",
              "10GB لكل صندوق بريد",
              "بريد احترافي باسم نطاقك",
              "دخول Webmail",
              "دخول من الكمبيوتر والجوال والتابلت",
              "حماية من الرسائل المزعجة والفيروسات",
              "دعم Outlook وتطبيقات البريد",
              "تحويل البريد والرد التلقائي",
              "أدوات نقل البريد"
            ]
          }
        },
        {
          "name": {
            "en": "Pro",
            "ar": "Pro"
          },
          "priceMonthly": 35,
          "orderUrl": "https://cp.skilledhost.com/domain-required?p=293507-1-lhr&t=36",
          "badge": {
            "en": "Business",
            "ar": "للأعمال"
          },
          "features": {
            "en": [
              "50 Business Mailboxes",
              "Free First-Year Domain",
              "10GB Storage per Mailbox",
              "Professional Email Using Your Domain",
              "Webmail Access",
              "Desktop, Mobile and Tablet Access",
              "Spam and Virus Protection",
              "Outlook and Email App Support",
              "Email Forwarding and Autoresponders",
              "Suitable for Departments and Staff Accounts"
            ],
            "ar": [
              "50 صندوق بريد أعمال",
              "نطاق مجاني للسنة الأولى",
              "10GB لكل صندوق بريد",
              "بريد احترافي باسم نطاقك",
              "دخول Webmail",
              "دخول من الكمبيوتر والجوال والتابلت",
              "حماية من الرسائل المزعجة والفيروسات",
              "دعم Outlook وتطبيقات البريد",
              "تحويل البريد والرد التلقائي",
              "مناسب للأقسام وحسابات الموظفين"
            ]
          }
        },
        {
          "name": {
            "en": "Ultimate",
            "ar": "Ultimate"
          },
          "priceMonthly": 56,
          "orderUrl": "https://cp.skilledhost.com/domain-required?p=293509-1-lhr&t=36",
          "badge": {
            "en": "Advanced",
            "ar": "متقدمة"
          },
          "features": {
            "en": [
              "Unlimited Business Mailboxes",
              "Free First-Year Domain",
              "10GB Storage per Mailbox",
              "Professional Email Using Your Domain",
              "Webmail Access",
              "Desktop, Mobile and Tablet Access",
              "Spam and Virus Protection",
              "Outlook and Email App Support",
              "Email Forwarding and Autoresponders",
              "Ideal for Larger Teams and Multiple Departments"
            ],
            "ar": [
              "صناديق بريد أعمال غير محدودة",
              "نطاق مجاني للسنة الأولى",
              "10GB لكل صندوق بريد",
              "بريد احترافي باسم نطاقك",
              "دخول Webmail",
              "دخول من الكمبيوتر والجوال والتابلت",
              "حماية من الرسائل المزعجة والفيروسات",
              "دعم Outlook وتطبيقات البريد",
              "تحويل البريد والرد التلقائي",
              "مناسب للفرق الكبيرة والأقسام المتعددة"
            ]
          }
        }
      ]
    }
  ]
}